{
  "codebook_schema_version": 1,
  "battery_version": "5.3.0",
  "participant_link_schema_version": "3",
  "signed_participant_links_supported": false,
  "participant_link_parameters": [
    "mode",
    "link_version",
    "battery_version",
    "deployment_id",
    "deployment_config_sha256",
    "session_type",
    "protocol",
    "protocol_version",
    "catalog_sha256",
    "stimulus_set",
    "manifest_sha256",
    "tasks",
    "feedback",
    "lang",
    "study_id",
    "condition_id",
    "site_id",
    "distribution_id",
    "study_title",
    "institution",
    "consent_version",
    "expected_minutes",
    "consent_url",
    "contact_url",
    "return_url"
  ],
  "checkpoint_schema_version": 3,
  "result_bundle_schema_version": 3,
  "csv_schemas": {
    "trial": {
      "11": {
        "columns": [
          "subject_id",
          "battery_version",
          "session_run_id",
          "configuration_source",
          "administration_mode",
          "session_type",
          "deployment_id",
          "deployment_environment",
          "deployment_config_schema_version",
          "deployment_config_sha256",
          "app_origin",
          "study_id",
          "condition_id",
          "site_id",
          "distribution_id",
          "study_title",
          "institution_name",
          "consent_version",
          "expected_minutes",
          "consent_url",
          "contact_url",
          "return_url",
          "consent_confirmed_at_utc",
          "preflight_completed_at_utc",
          "preflight_audio_passed",
          "session_status",
          "session_final_status",
          "session_started_at_utc",
          "session_ended_at_utc",
          "status_reason",
          "task_started_at_utc",
          "task_completed_at_utc",
          "app_build_id",
          "app_build_sha256",
          "app_script_sha256",
          "app_url",
          "participant_link_schema_version",
          "participant_link_validation_status",
          "configured_initial_language",
          "participant_link_config",
          "task_id",
          "task_label",
          "task_order",
          "trial",
          "stimulus_step",
          "stimulus_file_index",
          "stimulus_requested_step",
          "stimulus_requested_file_index",
          "stimulus_substituted",
          "odd_position",
          "correct_answer",
          "response",
          "correct",
          "rt_ms",
          "num_reversals_after",
          "step_before",
          "file_index_before",
          "step_after",
          "file_index_after",
          "step_size_used",
          "step_direction",
          "is_reversal",
          "reversal_number",
          "reversal_level",
          "mean_reversal_so_far",
          "threshold_estimate",
          "threshold_physical_value",
          "threshold_unit",
          "protocol_id",
          "protocol_version",
          "protocol_citation",
          "protocol_source_locator",
          "protocol_source_audit_status",
          "procedure_scope",
          "protocol_main_study_task_ids",
          "task_in_source_main_study",
          "stimulus_compatibility",
          "task_stimulus_compatibility",
          "max_trials",
          "target_reversals",
          "first_scored_reversal",
          "threshold_aggregation",
          "correct_responses_for_harder",
          "single_correct_before_first_incorrect",
          "step_sizes",
          "reversal_definition",
          "reversal_level_timing",
          "interstimulus_interval_ms",
          "post_sequence_delay_ms",
          "post_response_delay_ms",
          "practice_trials",
          "practice_feedback",
          "practice_standard_file_index",
          "practice_comparison_file_index",
          "task_order_method",
          "protocol_stimulus_binding_id",
          "stimulus_catalog",
          "stimulus_catalog_schema_version",
          "stimulus_catalog_sha256",
          "stimulus_set_id",
          "stimulus_set_version",
          "stimulus_set_kind",
          "stimulus_claim",
          "stimulus_parameter_profile_id",
          "stimulus_manifest",
          "stimulus_manifest_sha256",
          "stimulus_set_sha256",
          "stimulus_task_sha256",
          "stimulus_task_transformation",
          "stimulus_source_citation",
          "stimulus_source_locator",
          "stimulus_parent_set_id",
          "stimulus_parent_manifest",
          "stimulus_parent_set_sha256",
          "stimulus_parent_source_locator",
          "stimulus_source_archive_sha256",
          "stimulus_parent_source_archive_sha256",
          "stimulus_provenance_verification",
          "stimulus_validation_status",
          "stimulus_audit_date",
          "stimulus_generator",
          "stimulus_generator_version",
          "stimulus_generator_script",
          "stimulus_generator_script_sha256",
          "stimulus_parameters_file",
          "stimulus_parameters_sha256",
          "stimulus_license",
          "stimulus_license_note",
          "stimulus_standard_file_index",
          "stimulus_error_policy",
          "feedback_mode",
          "ui_language",
          "selected_task_ids",
          "replayed_interrupted_presentation",
          "interrupted_presentation_count",
          "visibility_interruption_count",
          "resume_count",
          "termination_reason",
          "scored_reversal_count",
          "reversal_levels_used",
          "threshold_available",
          "target_reversals_reached",
          "schema_version"
        ]
      }
    },
    "wide": {
      "9": {
        "base_columns": [
          "subject_id",
          "battery_version",
          "wide_schema_version",
          "session_run_id",
          "configuration_source",
          "administration_mode",
          "session_type",
          "deployment_id",
          "deployment_environment",
          "deployment_config_schema_version",
          "deployment_config_sha256",
          "app_origin",
          "study_id",
          "condition_id",
          "site_id",
          "distribution_id",
          "study_title",
          "institution_name",
          "consent_version",
          "expected_minutes",
          "consent_url",
          "contact_url",
          "return_url",
          "consent_confirmed_at_utc",
          "preflight_completed_at_utc",
          "preflight_audio_passed",
          "session_status",
          "status_reason",
          "session_started_at_utc",
          "session_ended_at_utc",
          "resume_count",
          "interrupted_presentation_count",
          "visibility_interruption_count",
          "app_build_id",
          "app_build_sha256",
          "app_script_sha256",
          "app_url",
          "participant_link_schema_version",
          "participant_link_validation_status",
          "configured_initial_language",
          "participant_link_config",
          "completed",
          "completed_at_utc",
          "protocol_id",
          "protocol_version",
          "protocol_citation",
          "protocol_source_locator",
          "protocol_source_audit_status",
          "procedure_scope",
          "protocol_main_study_task_ids",
          "stimulus_compatibility",
          "feedback_mode",
          "ui_language_at_start",
          "ui_language_at_completion",
          "ui_languages_used",
          "selected_task_ids",
          "task_order",
          "max_trials",
          "target_reversals",
          "first_scored_reversal",
          "threshold_aggregation",
          "correct_responses_for_harder",
          "single_correct_before_first_incorrect",
          "step_sizes",
          "reversal_definition",
          "reversal_level_timing",
          "task_order_method",
          "interstimulus_interval_ms",
          "post_sequence_delay_ms",
          "post_response_delay_ms",
          "practice_trials_per_task",
          "practice_feedback",
          "practice_standard_file_index",
          "practice_comparison_file_index",
          "stimulus_scale",
          "protocol_stimulus_binding_id",
          "stimulus_catalog",
          "stimulus_catalog_schema_version",
          "stimulus_catalog_sha256",
          "stimulus_set_id",
          "stimulus_set_version",
          "stimulus_set_kind",
          "stimulus_claim",
          "stimulus_parameter_profile_id",
          "stimulus_manifest",
          "stimulus_manifest_sha256",
          "stimulus_set_sha256",
          "stimulus_source_citation",
          "stimulus_source_locator",
          "stimulus_parent_set_id",
          "stimulus_parent_manifest",
          "stimulus_parent_set_sha256",
          "stimulus_parent_source_locator",
          "stimulus_source_archive_sha256",
          "stimulus_parent_source_archive_sha256",
          "stimulus_provenance_verification",
          "stimulus_validation_status",
          "stimulus_audit_date",
          "stimulus_generator",
          "stimulus_generator_version",
          "stimulus_generator_script",
          "stimulus_generator_script_sha256",
          "stimulus_parameters_file",
          "stimulus_parameters_sha256",
          "stimulus_license",
          "stimulus_license_note",
          "stimulus_standard_file_index",
          "stimulus_error_policy"
        ],
        "task_order": ["duration", "formant", "pitch", "risetime"],
        "task_columns": [
          "selected",
          "in_source_main_study",
          "stimulus_compatibility",
          "stimulus_task_sha256",
          "stimulus_task_transformation",
          "task_order",
          "threshold_file_index",
          "threshold_level",
          "threshold_physical_value",
          "threshold_unit",
          "trials_completed",
          "reversals_completed",
          "scored_reversal_count",
          "reversal_levels_used",
          "termination_reason",
          "threshold_available",
          "target_reversals_reached",
          "median_rt_ms",
          "practice_correct_count",
          "stimulus_substitution_count",
          "started_at_utc",
          "completed_at_utc"
        ]
      }
    }
  },
  "manifest_keys": {
    "top_level": [
      "result_bundle_schema_version",
      "generated_at_utc",
      "data_classification",
      "automatic_upload_performed",
      "administration_mode",
      "result_return_requires_external_portal_receipt",
      "deployment",
      "session",
      "study",
      "implementation",
      "procedure",
      "provenance",
      "files"
    ],
    "deployment": [
      "session_type",
      "deployment_id",
      "environment",
      "config_schema_version",
      "config_file",
      "config_sha256",
      "app_origin",
      "researcher_origin",
      "participant_origin",
      "public_participant_base_url"
    ],
    "session": [
      "subject_id",
      "session_run_id",
      "status",
      "status_reason",
      "started_at_utc",
      "ended_at_utc",
      "completed_at_utc",
      "resume_count",
      "interrupted_presentation_count",
      "visibility_interruption_count",
      "consent_confirmed_at_utc",
      "preflight_completed_at_utc",
      "preflight_audio_passed"
    ],
    "study": [
      "studyId",
      "conditionId",
      "siteId",
      "distributionId",
      "studyTitle",
      "institutionName",
      "consentVersion",
      "expectedMinutes",
      "consentUrl",
      "contactUrl",
      "returnUrl"
    ],
    "implementation": [
      "batteryVersion",
      "trialSchemaVersion",
      "wideSchemaVersion",
      "checkpointSchemaVersion",
      "resultBundleSchemaVersion",
      "appBuildId",
      "procedureScope",
      "taskOrderMethod",
      "reversalDefinition",
      "stimulusErrorPolicy",
      "app_build_sha256",
      "app_script_sha256",
      "served_asset_sha256",
      "app_url"
    ],
    "procedure": [
      "protocol_id",
      "protocol_version",
      "protocol_citation",
      "selected_task_ids",
      "task_order_ids",
      "feedback_mode"
    ],
    "provenance": [
      "protocol_stimulus_binding_id",
      "stimulus_catalog",
      "stimulus_catalog_schema_version",
      "stimulus_catalog_sha256",
      "stimulus_set_id",
      "stimulus_set_version",
      "stimulus_set_kind",
      "stimulus_claim",
      "stimulus_parameter_profile_id",
      "stimulus_manifest",
      "stimulus_manifest_sha256",
      "stimulus_set_sha256",
      "stimulus_source_citation",
      "stimulus_source_locator",
      "stimulus_parent_set_id",
      "stimulus_parent_manifest",
      "stimulus_parent_set_sha256",
      "stimulus_parent_source_locator",
      "stimulus_source_archive_sha256",
      "stimulus_parent_source_archive_sha256",
      "stimulus_provenance_verification",
      "stimulus_validation_status",
      "stimulus_audit_date",
      "stimulus_generator",
      "stimulus_generator_version",
      "stimulus_generator_script",
      "stimulus_generator_script_sha256",
      "stimulus_parameters_file",
      "stimulus_parameters_sha256",
      "stimulus_license",
      "stimulus_license_note",
      "stimulus_standard_file_index"
    ],
    "file_record": ["name", "media_type", "sha256"]
  },
  "tasks": {
    "duration": {"threshold_unit": "ms", "physical_per_level": 2.5},
    "formant": {"threshold_unit": "Hz", "physical_per_level": 2.0},
    "pitch": {"threshold_unit": "Hz", "physical_per_level": 0.3},
    "risetime": {"threshold_unit": "ms", "physical_per_level": 2.85}
  },
  "protocols": {
    "kachlicka2019": {
      "version": "kachlicka2019-staircase-v2",
      "stimulus_set_id": "kachlicka2019-reconstruction-v1",
      "parameter_profile_id": "kachlicka2019",
      "main_study_tasks": ["pitch", "formant", "duration", "risetime"],
      "available_tasks": ["pitch", "formant", "duration", "risetime"],
      "max_trials": 70,
      "target_reversals": 8,
      "first_scored_reversal": 2,
      "correct_responses_for_harder": 3,
      "single_correct_before_first_incorrect": 0,
      "step_sizes": "10|5|2|1|1|1|1|1",
      "reversal_level_timing": "before_step_update"
    },
    "sun2021": {
      "version": "sun2021-staircase-v3",
      "stimulus_set_id": "sun2021-reconstruction-v1",
      "parameter_profile_id": "sun2021",
      "main_study_tasks": ["pitch", "formant", "duration", "risetime"],
      "available_tasks": ["pitch", "formant", "duration", "risetime"],
      "max_trials": 70,
      "target_reversals": 8,
      "first_scored_reversal": 3,
      "correct_responses_for_harder": 2,
      "single_correct_before_first_incorrect": 1,
      "step_sizes": "10|5|2|1|1|1|1|1",
      "reversal_level_timing": "after_step_update"
    },
    "saitoTierney2024": {
      "version": "saito-tierney-2024-staircase-v1",
      "stimulus_set_id": "saito-tierney2024-reconstruction-v1",
      "parameter_profile_id": "saito_tierney2024",
      "main_study_tasks": ["formant", "pitch", "duration"],
      "available_tasks": ["pitch", "formant", "duration"],
      "max_trials": 70,
      "target_reversals": 8,
      "first_scored_reversal": 3,
      "correct_responses_for_harder": 3,
      "single_correct_before_first_incorrect": 0,
      "step_sizes": "10|5|1|1|1|1|1|1",
      "reversal_level_timing": "before_step_update"
    }
  },
  "validator_scope_exclusions": [
    "External return-portal receipt authenticity is not established by this self-consistency validator.",
    "The bundle has no external digital signature; this validator does not establish author identity or chain of custody."
  ]
}
